{"devices":[{"model":"tornado","color":"red","power":1200,"inserted":false,"mode":1,"time":0,"channel":0.0,"program":null,"volume":0},{"model":"rocks","color":"gray","power":45,"inserted":false,"volume":5,"channel":92.8,"time":0,"mode":0,"program":null},{"model":"lg","color":"white","power":120,"inserted":false,"volume":7,"channel":895.5,"time":0,"mode":0,"program":null},{"model":"supra","color":"silver","power":2200,"inserted":false,"program":"heating","time":5,"channel":0.0,"mode":0,"volume":0},{"model":"gorenje","color":"brown","power":1800,"inserted":false,"program":"easy","time":10,"channel":0.0,"mode":0,"volume":0},{"model":"aresa","color":"white","power":2000,"inserted":false,"mode":1,"time":0,"channel":0.0,"program":null,"volume":0}]}