{"name":"postWithNegativeAgeTest","id":"tests.TestPostDummy:postWithNegativeAgeTest","testCaseName":"tests.TestPostDummy","userStory":{"id":"tests.TestPostDummy","storyName":"Test post dummy","storyClassName":"tests.TestPostDummy","path":"tests","type":"story"},"featureTag":{"name":"Test post dummy","type":"story"},"title":"Post with negative age test","tags":[{"name":"Test post dummy","type":"story"}],"startTime":"2021-05-31T17:18:45.898521700+03:00[Europe/Minsk]","duration":1229,"testFailureCause":{"errorType":"java.lang.AssertionError","message":"expected:\u003c200\u003e but was:\u003c429\u003e","stackTrace":[{"classLoaderName":"app","declaringClass":"tests.TestPostDummy","methodName":"postWithNegativeAgeTest","fileName":"TestPostDummy.java","lineNumber":92,"format":1},{"moduleName":"java.base","moduleVersion":"11","declaringClass":"jdk.internal.reflect.NativeMethodAccessorImpl","methodName":"invoke0","fileName":"NativeMethodAccessorImpl.java","lineNumber":-2,"format":2},{"moduleName":"java.base","moduleVersion":"11","declaringClass":"jdk.internal.reflect.NativeMethodAccessorImpl","methodName":"invoke","fileName":"NativeMethodAccessorImpl.java","lineNumber":62,"format":2},{"moduleName":"java.base","moduleVersion":"11","declaringClass":"jdk.internal.reflect.DelegatingMethodAccessorImpl","methodName":"invoke","fileName":"DelegatingMethodAccessorImpl.java","lineNumber":43,"format":2},{"moduleName":"java.base","moduleVersion":"11","declaringClass":"jdk.internal.reflect.NativeMethodAccessorImpl","methodName":"invoke0","fileName":"NativeMethodAccessorImpl.java","lineNumber":-2,"format":2},{"moduleName":"java.base","moduleVersion":"11","declaringClass":"jdk.internal.reflect.NativeMethodAccessorImpl","methodName":"invoke","fileName":"NativeMethodAccessorImpl.java","lineNumber":62,"format":2},{"moduleName":"java.base","moduleVersion":"11","declaringClass":"jdk.internal.reflect.DelegatingMethodAccessorImpl","methodName":"invoke","fileName":"DelegatingMethodAccessorImpl.java","lineNumber":43,"format":2}]},"testFailureClassname":"java.lang.AssertionError","testFailureMessage":"expected:\u003c200\u003e but was:\u003c429\u003e","testFailureSummary":"FAILURE;java.lang.AssertionError;expected:\u003c200\u003e but was:\u003c429\u003e;TestPostDummy.java","projectKey":"","annotatedResult":"FAILURE","manual":false,"testSource":"JUnit","result":"FAILURE"}